{
  "results": {
    "underlying": {
      "url": "https://api.polygon.io/v2/aggs/ticker/CUBE/range/1/day/1634788800000/1643673600000?limit=165&sort=asc"
    },
    "values": [
      {
        "timestamp": 1641186000000,
        "value": 54.91923641703379
      },
      {
        "timestamp": 1641272400000,
        "value": 52.590589507842076
      },
      {
        "timestamp": 1641358800000,
        "value": 47.903293038766144
      },
      {
        "timestamp": 1641445200000,
        "value": 48.72357945172072
      },
      {
        "timestamp": 1641531600000,
        "value": 32.88647959461079
      },
      {
        "timestamp": 1641790800000,
        "value": 40.44687628580141
      },
      {
        "timestamp": 1641877200000,
        "value": 43.82147788568755
      },
      {
        "timestamp": 1641963600000,
        "value": 45.262401276402045
      },
      {
        "timestamp": 1642050000000,
        "value": 40.80515280218567
      },
      {
        "timestamp": 1642136400000,
        "value": 36.33207675280051
      },
      {
        "timestamp": 1642482000000,
        "value": 32.666605454203804
      },
      {
        "timestamp": 1642568400000,
        "value": 33.7168352188518
      },
      {
        "timestamp": 1642654800000,
        "value": 32.73494686338384
      },
      {
        "timestamp": 1642741200000,
        "value": 37.29715623486506
      },
      {
        "timestamp": 1643000400000,
        "value": 37.11021895431098
      },
      {
        "timestamp": 1643086800000,
        "value": 35.805669766188885
      },
      {
        "timestamp": 1643173200000,
        "value": 31.872951661100842
      },
      {
        "timestamp": 1643259600000,
        "value": 30.836733030321767
      },
      {
        "timestamp": 1643346000000,
        "value": 44.57552737988819
      },
      {
        "timestamp": 1643605200000,
        "value": 43.62643866908148
      }
    ]
  },
  "status": "OK",
  "request_id": "a54e061acb2e61d7aa3feb240510cd63"
}